heritrix3/__init__.py
heritrix3/__main__.py
heritrix3/api.py
heritrix3/cli.py
heritrix3-0.4.1.dist-info/AUTHORS.rst
heritrix3-0.4.1.dist-info/LICENSE
heritrix3-0.4.1.dist-info/METADATA
heritrix3-0.4.1.dist-info/WHEEL
heritrix3-0.4.1.dist-info/entry_points.txt
heritrix3-0.4.1.dist-info/top_level.txt
heritrix3-0.4.1.dist-info/RECORD
