Metadata-Version: 2.1
Name: heritrix3
Version: 0.4.1
Summary: A internetarchive/heritrix3 python REST API client.
Home-page: https://github.com/Querela/python-heritrix3-client
Author: Erik Körner
Author-email: koerner@informatik.uni-leipzig.de
License: MIT
Project-URL: Documentation, https://python-heritrix3-client.readthedocs.io/
Project-URL: Changelog, https://python-heritrix3-client.readthedocs.io/en/latest/changelog.html
Project-URL: Issue Tracker, https://github.com/Querela/python-heritrix3-client/issues
Keywords: heritrix,api
Platform: UNKNOWN
Classifier: Development Status :: 5 - Production/Stable
Classifier: Intended Audience :: Developers
Classifier: License :: OSI Approved :: MIT License
Classifier: Operating System :: Unix
Classifier: Operating System :: POSIX
Classifier: Operating System :: Microsoft :: Windows
Classifier: Programming Language :: Python
Classifier: Programming Language :: Python :: 3
Classifier: Programming Language :: Python :: 3 :: Only
Classifier: Programming Language :: Python :: 3.10
Classifier: Programming Language :: Python :: 3.6
Classifier: Programming Language :: Python :: 3.7
Classifier: Programming Language :: Python :: 3.8
Classifier: Programming Language :: Python :: 3.9
Classifier: Programming Language :: Python :: Implementation :: CPython
Classifier: Programming Language :: Python :: Implementation :: PyPy
Classifier: Topic :: Utilities
Requires-Python: >=3.6
Requires-Dist: click
Requires-Dist: lxml
Requires-Dist: requests
Provides-Extra: cli
Requires-Dist: pygments ; extra == 'cli'
